pylinalg/__init__.py
pylinalg/matrix.py
pylinalg/misc.py
pylinalg/quaternion.py
pylinalg/vector.py
pylinalg-0.6.6.dist-info/licenses/LICENSE
pylinalg-0.6.6.dist-info/WHEEL
pylinalg-0.6.6.dist-info/METADATA
pylinalg-0.6.6.dist-info/RECORD
