Metadata-Version: 2.4
Name: pylinalg
Version: 0.6.6
Summary: Linear algebra utilities for Python
Keywords: graphics,3d,linear algebra
Author: Almar Klein, Korijn van Golen
Requires-Python: >= 3.9
License-File: LICENSE
Requires-Dist: numpy>=1.20.0
Requires-Dist: pylinalg[lint, tests, docs] ; extra == "dev"
Requires-Dist: sphinx>7.2 ; extra == "docs"
Requires-Dist: sphinx_rtd_theme ; extra == "docs"
Requires-Dist: ruff ; extra == "lint"
Requires-Dist: pytest ; extra == "tests"
Requires-Dist: pytest-cov ; extra == "tests"
Requires-Dist: pytest-watcher ; extra == "tests"
Requires-Dist: hypothesis[numpy]~=6.61.0 ; extra == "tests"
Requires-Dist: packaging ; extra == "tests"
Requires-Dist: twine ; extra == "tests"
Requires-Dist: scipy ; extra == "tests"
Project-URL: Repository, https://github.com/pygfx/pylinalg
Provides-Extra: dev
Provides-Extra: docs
Provides-Extra: lint
Provides-Extra: tests
